defines.py
main.py
qinfo_gui-0.0.3.dist-info/LICENSE.md
qinfo_gui-0.0.3.dist-info/METADATA
qinfo_gui-0.0.3.dist-info/WHEEL
qinfo_gui-0.0.3.dist-info/entry_points.txt
qinfo_gui-0.0.3.dist-info/top_level.txt
qinfo_gui-0.0.3.dist-info/RECORD
