Metadata-Version: 2.1
Name: qinfo-gui
Version: 0.0.3
Summary: A gui for qinfo
Home-page: https://github.com/El-Wumbus/qinfo-gui
Author: Decator (Aidan Neal)
Author-email: decator.c@proton.me
License: LGPLv3
Keywords: python,gui,gtk
Platform: UNKNOWN
Classifier: Programming Language :: Python :: 3
Classifier: Intended Audience :: End Users/Desktop
Classifier: Operating System :: Unix
License-File: LICENSE.md
Requires-Dist: qinfo-python (==0.1.3)
